toodoot/__init__.py
toodoot/markdowntasks.py
toodoot/toodoot.py
toodoot/widgets.py
toodoot-0.0.7.dist-info/LICENSE
toodoot-0.0.7.dist-info/METADATA
toodoot-0.0.7.dist-info/WHEEL
toodoot-0.0.7.dist-info/entry_points.txt
toodoot-0.0.7.dist-info/top_level.txt
toodoot-0.0.7.dist-info/RECORD
