Metadata-Version: 2.1
Name: toodoot
Version: 0.0.7
Summary: Manage todos with markdown formatting from a convenient TUI
Author-email: Hunter Dyar <me@hdyar.com>
License: The MIT License (MIT)
Project-URL: Home, https://github.com/hunterdyar/toodoot
Project-URL: Source, https://github.com/hunterdyar/toodoot
Classifier: License :: OSI Approved :: MIT License
License-File: LICENSE
